<?xml version="1.0"?>
<facelet-taglib version="2.0"
	xmlns="http://java.sun.com/xml/ns/javaee"
	xmlns:xsi="http://www.w3.org/2001/XMLSchema-instance"
	xsi:schemaLocation="http://java.sun.com/xml/ns/javaee http://java.sun.com/xml/ns/javaee/web-facelettaglibrary_2_0.xsd">
	<namespace>http://mkremer.lu/facelets</namespace>
	<tag>
		<tag-name>tweed</tag-name>
		<source>tags/lu/mkremer/webprogsga/tweed.xhtml</source>
		<attribute>
			<name>value</name>
			<required>true</required>
			<type>lu.mkremer.webprogsga.persistence.Tweed</type>
		</attribute>
		<attribute>
			<name>onreply</name>
			<required>false</required>
			<type>java.lang.String</type>
		</attribute>
		<attribute>
			<name>look</name>
			<required>false</required>
			<type>java.lang.String</type>
		</attribute>
		<attribute>
			<name>outcome</name>
			<required>false</required>
			<type>java.lang.String</type>
		</attribute>
		<attribute>
			<name>param</name>
			<required>false</required>
			<type>java.lang.String</type>
		</attribute>
		<attribute>
			<name>collapsible</name>
			<required>false</required>
			<type>java.lang.Boolean</type>
		</attribute>
	</tag>
	<tag>
		<tag-name>restricted</tag-name>
		<source>tags/lu/mkremer/webprogsga/restricted.xhtml</source>
		<attribute>
			<name>condition</name>
			<required>true</required>
			<type>java.lang.Boolean</type>
		</attribute>
		<attribute>
			<name>message</name>
			<required>false</required>
			<type>java.lang.String</type>
		</attribute>
		<attribute>
			<name>severity</name>
			<required>false</required>
			<type>java.lang.String</type>
		</attribute>
	</tag>
</facelet-taglib>